{"id":"ecard3-134","name":"Mystery Plate β","supertype":"Trainer","subtypes":["Technical Machine"],"rules":["Attach this card to 1 of your Pokémon in play. That Pokémon may use this card's attack instead of its own. At the end of your turn, discard Mystery Plate β."],"attacks":[{"name":"Stone Crush","cost":["Colorless"],"convertedEnergyCost":1,"damage":"","text":"If your opponent has 5 or more Prizes, draw 3 cards. If your opponent has only 1 Prize, choose 2 Energy cards attached to the Defending Pokémon (1 if there is only 1). Your opponent shuffles those cards into his or her deck."}],"set":{"id":"ecard3","name":"Skyridge","series":"E-Card","printedTotal":144,"total":182,"legalities":{"unlimited":"Legal"},"ptcgoCode":"SK","releaseDate":"2003/05/12","updatedAt":"2020/08/14 09:35:00","images":{"symbol":"https://images.pokemontcg.io/ecard3/symbol.png","logo":"https://images.pokemontcg.io/ecard3/logo.png"}},"number":"134","artist":"Hiromichi Sugiyama","rarity":"Uncommon","legalities":{"unlimited":"Legal"},"images":{"small":"https://images.pokemontcg.io/ecard3/134.png","large":"https://images.pokemontcg.io/ecard3/134_hires.png"},"tcgplayer":{"url":"https://prices.pokemontcg.io/tcgplayer/ecard3-134","updatedAt":"2023/09/09","prices":{"normal":{"low":2.25,"mid":3.99,"high":6.99,"market":2.99,"directLow":3.99},"reverseHolofoil":{"low":19.94,"mid":85.61,"high":85.62,"market":17.99,"directLow":null}}},"cardmarket":{"url":"https://prices.pokemontcg.io/cardmarket/ecard3-134","updatedAt":"2023/09/09","prices":{"averageSellPrice":1.42,"lowPrice":0.05,"trendPrice":2.15,"germanProLow":0.0,"suggestedPrice":0.0,"reverseHoloSell":0.0,"reverseHoloLow":1.88,"reverseHoloTrend":7.94,"lowPriceExPlus":0.66,"avg1":0.7,"avg7":1.42,"avg30":1.83,"reverseHoloAvg1":1.79,"reverseHoloAvg7":4.56,"reverseHoloAvg30":5.93}}}